skyshapython/__init__.py
skyshapython/maxheap.py
skyshapython/minheap.py
skyshapython/sort_master.py
tests/__init__.py
tests/test_max_heaps.py
tests/test_min_heaps.py
tests/test_sort_master.py
skyshapython-0.3.1.dist-info/LICENSE
skyshapython-0.3.1.dist-info/METADATA
skyshapython-0.3.1.dist-info/WHEEL
skyshapython-0.3.1.dist-info/top_level.txt
skyshapython-0.3.1.dist-info/RECORD
