Metadata-Version: 2.1
Name: skyshapython
Version: 0.3.1
Summary: A Python library for utilities and wrappers for frequently used functionality.
Home-page: https://github.com/skywalker94/skyshapython
Author: Sharangdeo Bhagwat
Author-email: sharangdeo@protonmail.com
License: MIT
Project-URL: Bug Tracker, https://github.com/skywalker94/skyshapython/issues
Project-URL: Source Code, https://github.com/skywalker94/skyshapython
Platform: UNKNOWN
Classifier: Programming Language :: Python :: 3
Classifier: License :: OSI Approved :: MIT License
Classifier: Operating System :: OS Independent
Requires-Python: >=3.6
